susan/__init__.py
susan/api.py
susan/cli.py
susan/config.py
susan/db.py
susan-0.0.2.dist-info/DESCRIPTION.rst
susan-0.0.2.dist-info/METADATA
susan-0.0.2.dist-info/RECORD
susan-0.0.2.dist-info/WHEEL
susan-0.0.2.dist-info/entry_points.txt
susan-0.0.2.dist-info/metadata.json
susan-0.0.2.dist-info/top_level.txt
