Metadata-Version: 2.0
Name: susan
Version: 0.0.2
Summary: Simple CLI note taker and free-wheeling wiki
Home-page: https://github.com/undeadparrot/susan
Author: Shane Matuszek
Author-email: smatuszeksa@gmail.com
License: MIT
Keywords: note wiki todo cli
Platform: UNKNOWN
Classifier: Development Status :: 3 - Alpha
Classifier: License :: OSI Approved :: MIT License
Classifier: Programming Language :: Python :: 3
Classifier: Environment :: Console
Classifier: Intended Audience :: End Users/Desktop
Classifier: Intended Audience :: Developers
Classifier: Operating System :: MacOS
Classifier: Operating System :: Microsoft
Classifier: Operating System :: POSIX
Classifier: Topic :: Database
Classifier: Topic :: Education
Classifier: Topic :: Utilities
Classifier: Topic :: Internet :: WWW/HTTP :: Dynamic Content :: News/Diary
Classifier: Topic :: Office/Business :: News/Diary
Requires-Dist: click
Requires-Dist: sqlalchemy
